setup.py
bin/configure
src/configure/__init__.py
src/configure/build.py
src/configure/command.py
src/configure/compiler.py
src/configure/env.py
src/configure/filesystem.py
src/configure/generator.py
src/configure/node.py
src/configure/path.py
src/configure/platform.py
src/configure/project.py
src/configure/source.py
src/configure/target.py
src/configure/tools.py
src/configure.py.egg-info/PKG-INFO
src/configure.py.egg-info/SOURCES.txt
src/configure.py.egg-info/dependency_links.txt
src/configure.py.egg-info/top_level.txt
src/configure/dependency/__init__.py
src/configure/dependency/autotools.py
src/configure/dependency/cmake.py
src/configure/generators/__init__.py
src/configure/generators/find_dependencies.py
src/configure/generators/makefile.py
src/configure/generators/tup.py
src/configure/lang/__init__.py
src/configure/lang/c/__init__.py
src/configure/lang/c/clang.py
src/configure/lang/c/compiler.py
src/configure/lang/c/gcc.py
src/configure/lang/c/library.py
src/configure/lang/c/msvc.py
src/configure/lang/c/libraries/__init__.py
src/configure/lang/c/libraries/curl.py
src/configure/lang/c/libraries/freetype.py
src/configure/lang/c/libraries/opengl.py
src/configure/lang/c/libraries/python.py
src/configure/lang/c/libraries/sdl.py
src/configure/lang/cxx/__init__.py
src/configure/lang/cxx/clang.py
src/configure/lang/cxx/compiler.py
src/configure/lang/cxx/gcc.py
src/configure/lang/cxx/library.py
src/configure/lang/cxx/msvc.py
src/configure/lang/cxx/libraries/__init__.py
src/configure/lang/cxx/libraries/boost.py
src/configure/templates/__init__.py
src/configure/templates/project.py