Metadata-Version: 1.0
Name: configure.py
Version: 1.1
Summary: Configure your project's builds in plain Python
Home-page: http://github.com/hotgloupi/configure.py
Author: Raphaël Londeix
Author-email: raphael.londeix@gmail.com
License: UNKNOWN
Platform: UNKNOWN
